aaa_features/__init__.py
aaa_features/features.py
aaa_features/featuresFunctions.py
aaa_features/tools.py
aaa_features-0.2.1.dist-info/LICENSE_EN.txt
aaa_features-0.2.1.dist-info/LICENSE_FR.txt
aaa_features-0.2.1.dist-info/METADATA
aaa_features-0.2.1.dist-info/WHEEL
aaa_features-0.2.1.dist-info/top_level.txt
aaa_features-0.2.1.dist-info/RECORD
