Metadata-Version: 2.1
Name: aaa-features
Version: 0.2.1
Summary: Python code to calculate signal features. This code was extracted from https://github.com/malfante/AAA
Home-page: https://github.com/awacero/aaa_features
Author: Marielle Malfante
Author-email: marielle.malfante@gmail.com
License: UNKNOWN
Platform: UNKNOWN
Classifier: Programming Language :: Python :: 3
Classifier: License :: CeCILL-B Free Software License Agreement (CECILL-B)
Classifier: Operating System :: OS Independent
License-File: LICENSE_EN.txt
License-File: LICENSE_FR.txt
Requires-Dist: obspy (>=1.1.0)
Requires-Dist: python-speech-features (>=0.6)
Requires-Dist: sympy (>=1.8)
